[{"top_text": "Hoss call me ", "meme_type": "redditors-wife", "bottom_text": " After this Gb "},
{"top_text": "i asked what he was doing ", "meme_type": "redditors-wife", "bottom_text": " HE TOLD ME HE WAS LIKING AIMEE CLARK'S POST. "},
{"top_text": "PREFERIVO BECCARLO SU YOUPORN ", "meme_type": "redditors-wife", "bottom_text": " CHE VEDERLO SU YOUTUBE A VEDERE I VIDEO DI MORENO "},
{"top_text": " ", "meme_type": "redditors-wife", "bottom_text": " TOO BUSY MAKING ALiVE "},
{"top_text": "i am addicted ", "meme_type": "redditors-wife", "bottom_text": " to supreme dragon ball wiki "},
{"top_text": "Honey, stop working on your powerpoint ", "meme_type": "redditors-wife", "bottom_text": " everyone getting mad "},
{"top_text": "babe come to bed ", "meme_type": "redditors-wife", "bottom_text": " ill be there soon just laughing at this guys joke "},
{"top_text": "Honey come to bed ", "meme_type": "redditors-wife", "bottom_text": " did you know that the united states is the only first"},
{"top_text": "akshay watching porn ", "meme_type": "redditors-wife", "bottom_text": " bua watchin from behind.. "},
{"top_text": "i asked him to get off the computer ", "meme_type": "redditors-wife", "bottom_text": " so he could take me to the retreat which is open to both genders "},
{"top_text": "honey come to bead ", "meme_type": "redditors-wife", "bottom_text": " we have universal healthcare "},
{"top_text": "Asked Him To Come To Bed ", "meme_type": "redditors-wife", "bottom_text": " He Said He Had To See What The Other Countries Didn't Want Him To See "},
{"top_text": "I told him to come to bed... ", "meme_type": "redditors-wife", "bottom_text": " He told me to get the dog shit out of the N64 "},
{"top_text": "i GROUNDED MY SON ", "meme_type": "redditors-wife", "bottom_text": " He said \"probation for 5 minutes\" "},
{"top_text": "when your whoring around on wireclub ", "meme_type": "redditors-wife", "bottom_text": " think about your wife! "},
{"top_text": "ASK WHEN HE'S FINALLY GOING TO PROPOSE ", "meme_type": "redditors-wife", "bottom_text": " \"NOT UNTIL YOU GET A MANICURE\" "},
{"top_text": "PREFERIVO BECCARLO SU  ", "meme_type": "redditors-wife", "bottom_text": "  "},
{"top_text": "when your whoring around on wireclub ", "meme_type": "redditors-wife", "bottom_text": " think about your wife! "},
{"top_text": "Drago messaged me! ", "meme_type": "redditors-wife", "bottom_text": " I think he loves me "},
{"top_text": "Honey come to bed? ", "meme_type": "redditors-wife", "bottom_text": " Fuck off Taylor blew it. "},
{"top_text": "TOLD MY WIFE 5 MINUTES ", "meme_type": "redditors-wife", "bottom_text": " STAYED THERE WATCHING VIDEOS FOR 3 HOURS "},
{"top_text": "I ASKED WHEN HE WOULD PROPOSE ", "meme_type": "redditors-wife", "bottom_text": " \"NOT UNTIL YOU GET A PEDICURE\" "},
{"top_text": "honey, stop working on your powerpoint ", "meme_type": "redditors-wife", "bottom_text": " eveyone is getting mad "},
{"top_text": "i asked him he wanted to order a pizza ", "meme_type": "redditors-wife", "bottom_text": " he told me to jump off a bridge "},
{"top_text": "honey come to bed ", "meme_type": "redditors-wife", "bottom_text": " hold on honey"},
{"top_text": "are you coming to bed? ", "meme_type": "redditors-wife", "bottom_text": " shut up bitch, i am on cowyard! "},
{"top_text": "akshay watching porn ", "meme_type": "redditors-wife", "bottom_text": " bua watchin from behind.. "},
{"top_text": "i told him i got our son a rc plane and ", "meme_type": "redditors-wife", "bottom_text": " he said LOL spy plane inbound "},
{"top_text": "Are you coming to bed, Honey? ", "meme_type": "redditors-wife", "bottom_text": " \" People estimate he killed 20"},
{"top_text": "akshay watching porn ", "meme_type": "redditors-wife", "bottom_text": " bua watchin from behind.. "},
{"top_text": "He said \"let's get your nails done\" ", "meme_type": "redditors-wife", "bottom_text": " Still waiting for the proposal "},
{"top_text": "i told him i got our son a rc plane and ", "meme_type": "redditors-wife", "bottom_text": " he said \"LOL spy plane inbound\" "},
{"top_text": "i told him if he came to bed he'd get a surprise ", "meme_type": "redditors-wife", "bottom_text": " he said you're gonna make ron paul president? "},
{"top_text": "i'm getting arrested for not voting for elizabeth as vp ", "meme_type": "redditors-wife", "bottom_text": " lol XD putting this on facebook "},
{"top_text": "I SAID GO TO BED.... ", "meme_type": "redditors-wife", "bottom_text": " HE SAID GO KILL YOURSELF "},
{"top_text": "Supreme dragon ball wiki ", "meme_type": "redditors-wife", "bottom_text": " i love to edit "},
{"top_text": "you're lying.. ", "meme_type": "redditors-wife", "bottom_text": " i'm watching you "},
{"top_text": "bugun hic kutsal kitap okumadi ", "meme_type": "redditors-wife", "bottom_text": " yaptigi tek sey dizi izlemek ve facebook'ta oturmak "},
{"top_text": "I asked him why we were pulling over ", "meme_type": "redditors-wife", "bottom_text": " Joey needs help "},
{"top_text": "I ASKED TO GO TO A MOVIE ", "meme_type": "redditors-wife", "bottom_text": " HE SAID NO! "},
{"top_text": "i TOLD HIM OUR SON TURNED SIX ", "meme_type": "redditors-wife", "bottom_text": " HE SAID DID HE EVOLVE HIS W YET "},
{"top_text": "babe come to bed... ", "meme_type": "redditors-wife", "bottom_text": " no hoe im turnt "},
{"top_text": "I asked him what he wanted for dinner ", "meme_type": "redditors-wife", "bottom_text": " He said about tree fiddy "},
{"top_text": "I told him i understood Romeo & Juliet he said ", "meme_type": "redditors-wife", "bottom_text": " Pics or it didn't happen "},
{"top_text": "pah uang bulanan habis ", "meme_type": "redditors-wife", "bottom_text": " tenang, papah print lagi "},
{"top_text": "I asked him to come to bed ", "meme_type": "redditors-wife", "bottom_text": " He told me to clean the dog shit out of the N64 "},
{"top_text": "I told him I had a miscarriage ", "meme_type": "redditors-wife", "bottom_text": " he said yolo "},
{"top_text": "ASKED HIM TO CLEAN THE DESK ", "meme_type": "redditors-wife", "bottom_text": " TOO BUSY CODING ALIVE "},
{"top_text": "I asked him if we were going to protest ", "meme_type": "redditors-wife", "bottom_text": " \"What does it look like I'm doing?\" "},
{"top_text": "I saw him watching  ", "meme_type": "redditors-wife", "bottom_text": " k"},
{"top_text": "i can't park in italy ", "meme_type": "redditors-wife", "bottom_text": " he tells his class and laughs about it "},
{"top_text": "You think I don't see you ", "meme_type": "redditors-wife", "bottom_text": " watching porn "},
{"top_text": "i love to edit ", "meme_type": "redditors-wife", "bottom_text": " supreme dragon ball wiki "},
{"top_text": "Told him i was frg leader ", "meme_type": "redditors-wife", "bottom_text": " won't go out in public "},
{"top_text": "Asked him to clean the desk ", "meme_type": "redditors-wife", "bottom_text": " TO busy making alive "},
{"top_text": "Wants anal ", "meme_type": "redditors-wife", "bottom_text": " Ebay doesn't sell anal "},
{"top_text": "I asked him if I could sing him a song I wrote ", "meme_type": "redditors-wife", "bottom_text": "  he said he would rather listen to his mother being raped "},
{"top_text": "Every since the NBA playoffs ", "meme_type": "redditors-wife", "bottom_text": " I have been dead to him "},
{"top_text": "ds ", "meme_type": "redditors-wife", "bottom_text": "  "},
{"top_text": "Schatz grad nicht ", "meme_type": "redditors-wife", "bottom_text": " Helms spielt wieder Blitzcrank "},
{"top_text": "i asked him to come to bed ", "meme_type": "redditors-wife", "bottom_text": " he said he's pwning teahadists on facebook. "},
{"top_text": "ASKED HIM TO LEAD ME TO PARIS ", "meme_type": "redditors-wife", "bottom_text": " HE OFFERS ME TO PLAY FOOTBALL MANAGER "},
{"top_text": "ryan left me  ", "meme_type": "redditors-wife", "bottom_text": " I forgot a full stop "},
{"top_text": " ", "meme_type": "redditors-wife", "bottom_text": " come back to bed tiarnan "},
{"top_text": "To think that I was the one ", "meme_type": "redditors-wife", "bottom_text": " Who introduced him to reddit "},
{"top_text": "I TOLD HIM HE MAKE TOO MUCH NOISE ", "meme_type": "redditors-wife", "bottom_text": " REPORT FDP NOOB "},
{"top_text": "Listen... I'm sorry, it's over. ", "meme_type": "redditors-wife", "bottom_text": " GG "},
{"top_text": "He's up all nite on ", "meme_type": "redditors-wife", "bottom_text": " Tony Burks rat Rod FB site again :[ "},
{"top_text": "he is looking at that trash again ", "meme_type": "redditors-wife", "bottom_text": " wait until he is sleeping with trash on him "},
{"top_text": "why wont he pay attention to me. ", "meme_type": "redditors-wife", "bottom_text": " \"to busy clicking nessa\" "},
{"top_text": "PREFERIVO BECCARLO SU YOUPORN A SMANETTARSI ", "meme_type": "redditors-wife", "bottom_text": " PIUTTOSTO DI SCOPRIRE CHE SI ASCOLTA MORENO SU YOUTUBE "},
{"top_text": "Asked him to come to bed ", "meme_type": "redditors-wife", "bottom_text": " He said is isn't finished protesting the NSA "},
{"top_text": "Honey come to bed? ", "meme_type": "redditors-wife", "bottom_text": " Fuck off Taylor blew it. "},
{"top_text": "akshay watching porn ", "meme_type": "redditors-wife", "bottom_text": " bua watchin from behind.. "},
{"top_text": "I told him to come to be ", "meme_type": "redditors-wife", "bottom_text": " He said he was going to do a puzzle first  "},
{"top_text": "shit ka lakas mong manood peru dmo kayang gawin sakin ", "meme_type": "redditors-wife", "bottom_text": "  "},
{"top_text": "I asked to have a word ", "meme_type": "redditors-wife", "bottom_text": " Antihydroautodefenestratophiliphobiphiliaizationist "},
{"top_text": "scumbag dota ", "meme_type": "redditors-wife", "bottom_text": " destroying relationship "},
{"top_text": "I JUST CANT ", "meme_type": "redditors-wife", "bottom_text": " TOP KEK LEL MAYMAY "},
{"top_text": "It's not against the law ", "meme_type": "redditors-wife", "bottom_text": " to study!!!! "},
{"top_text": "i asked him if he wanted to order a pizza ", "meme_type": "redditors-wife", "bottom_text": " he told me to jump off a bridge "},
{"top_text": "I asked if our Love could come back ", "meme_type": "redditors-wife", "bottom_text": " He said I missed my chance at old memes "},
{"top_text": "Caught herman ", "meme_type": "redditors-wife", "bottom_text": " having a gay video chat last night "},
{"top_text": "Mom knows i watch porn ", "meme_type": "redditors-wife", "bottom_text": " but then she figures out i was watching her  "},
{"top_text": "I asked for him to call me a sexy name in bed ", "meme_type": "redditors-wife", "bottom_text": " He called me an Antihydroautodefenestratophiliphobiphiliaizationist "},
{"top_text": "MID MID MID I SAID MID FIRST ", "meme_type": "redditors-wife", "bottom_text": " fUCKING INSTALOCKER REPORT FDP NOOB "},
{"top_text": "Hey honey, I was thinking for dinner tonight we could try ", "meme_type": "redditors-wife", "bottom_text": " "},
{"top_text": "I told him i may throw myself out of the window ", "meme_type": "redditors-wife", "bottom_text": " He said not to do it underwater "},
{"top_text": "I asked him to come to bed ", "meme_type": "redditors-wife", "bottom_text": " He said he needed to check under the toilet seat first "},
{"top_text": "NO BITCH ", "meme_type": "redditors-wife", "bottom_text": " THERE IS A PARTICULAR FORMULA "},
{"top_text": "i asked him to come to bed ", "meme_type": "redditors-wife", "bottom_text": " he said he's pwning teahadists on facebook. "},
{"top_text": "Stoneguy223 ", "meme_type": "redditors-wife", "bottom_text": "  "},
{"top_text": "why wont he pay attention to me. ", "meme_type": "redditors-wife", "bottom_text": "  "},
{"top_text": "I ASKED HIM IF I COULD LEAD HIM AROUND THE WORLD. ", "meme_type": "redditors-wife", "bottom_text": " HE SAID REDDIT ALREADY SHOWED HIM THE WORLD. "},
{"top_text": "omg. my husband is talking ", "meme_type": "redditors-wife", "bottom_text": " to a freshman name jacob "},
{"top_text": "  ", "meme_type": "redditors-wife", "bottom_text": "  "},
{"top_text": "\"It's getting late, come to bed\" ", "meme_type": "redditors-wife", "bottom_text": " \"I'm still to upvote my first non"},
{"top_text": "I told him I had a miscarriage ", "meme_type": "redditors-wife", "bottom_text": " he said yolo "},
{"top_text": "I suggested we make a sex movie ", "meme_type": "redditors-wife", "bottom_text": " He said we should hold auditions for my part "},
{"top_text": "i asked him to put labels on the corn we are freezing ", "meme_type": "redditors-wife", "bottom_text": " he wrote tl;dr on all of them "},
{"top_text": "Just married a mexican 9", "meme_type": "redditors-wife", "bottom_text": "gagger "},
{"top_text": "akshay watching porn ", "meme_type": "redditors-wife", "bottom_text": " bua watchin from behind.. "},
{"top_text": "I asked him to cuddle ", "meme_type": "redditors-wife", "bottom_text": " he told me to keep my bruises "}]